<?xml version="1.0" encoding="ISO-8859-1"?>
<FreightInvoiceExt>
   <Envelope>
      <SenderIdentification>MXMEX02</SenderIdentification>
      <ReceiverIdentification>USJFK15</ReceiverIdentification>
      <MessageType>FRTINV</MessageType>
      <MessageVersion>01.00</MessageVersion>
      <EnvelopeIdentification>3572</EnvelopeIdentification>
      <TransmissionDateTime>
         <Date>2016-03-29</Date>
         <Time>17:39:02.0Z</Time>
      </TransmissionDateTime>
   </Envelope>
   <Message>
      <InvoiceHeader>
         <InvoiceType>S</InvoiceType>
         <InvoiceNumber>MEXI164171</InvoiceNumber>
         <InvoiceDate>2016-03-29</InvoiceDate>
         <InvoiceDueDate>2016-06-27</InvoiceDueDate>
         <CreditDebitFlag>D</CreditDebitFlag>
         <InvoiceToAddress>
            <PartyInformation>
               <PartyName>Schering-Plough, S.A. de C.V.</PartyName>
               <Street>Calle 16 de Septiembre 301</Street>
               <City>Mexico</City>
               <StateRegionCode>DF</StateRegionCode>
               <CountryCode>MX</CountryCode>
               <KNAddressCode>1000138525</KNAddressCode>
            </PartyInformation>
            <AccountNo>3002373</AccountNo>
            <VATNo>MXSPL910701FD9</VATNo>
         </InvoiceToAddress>
         <InvoicedByAddress>
            <PartyInformation>
               <PartyName>Kuehne + Nagel S.A. DE C.V.</PartyName>
               <Street>Calle 28 NO. 90-A</Street>
               <City>Mexico</City>
               <StateRegionCode>DF</StateRegionCode>
               <CountryCode>MX</CountryCode>
               <KNAddressCode>1000099179</KNAddressCode>
            </PartyInformation>
            <VATNo>MXNA</VATNo>
         </InvoicedByAddress>
      </InvoiceHeader>
      <InvoiceDetails>
         <KNFileReference>1007953803</KNFileReference>
         <InvoiceAmount>
            <Value>15829.10</Value>
            <Currency>MXN</Currency>
         </InvoiceAmount>
         <VATDetails>
            <VATText>STANDARD 16%</VATText>
            <VATBaseValue>
               <Value>3352.52</Value>
               <Currency>MXN</Currency>
            </VATBaseValue>
            <VATValue>
               <Value>536.40</Value>
               <Currency>MXN</Currency>
            </VATValue>
            <VATRate>16.00</VATRate>
         </VATDetails>
         <ChargeDetails>
            <ChargeCode>550</ChargeCode>
            <CreditDebitFlag>D</CreditDebitFlag>
            <ChargeDescription>Seafreight</ChargeDescription>
            <ChargeAmount>
               <Value>1222.27</Value>
               <Currency>MXN</Currency>
            </ChargeAmount>
            <VATPercentage>0.00</VATPercentage>
            <ChargeRemarks/>
            <CalculationQuantity>
               <Value>0.001</Value>
            </CalculationQuantity>
            <CalculationRate>70.00</CalculationRate>
            <ForeignChargeAmount>
               <Value>70.00</Value>
               <Currency>USD</Currency>
            </ForeignChargeAmount>
            <ExchangeRate>17.461</ExchangeRate>
         </ChargeDetails>
         <ChargeDetails>
            <ChargeCode>163</ChargeCode>
            <CreditDebitFlag>D</CreditDebitFlag>
            <ChargeDescription>Precarriage Charge</ChargeDescription>
            <ChargeAmount>
               <Value>7387.87</Value>
               <Currency>MXN</Currency>
            </ChargeAmount>
            <VATPercentage>0.00</VATPercentage>
            <ChargeRemarks/>
            <CalculationQuantity>
               <Value>0.001</Value>
            </CalculationQuantity>
            <CalculationRate>540.00</CalculationRate>
            <ForeignChargeAmount>
               <Value>368.28</Value>
               <Currency>EUR</Currency>
            </ForeignChargeAmount>
            <ExchangeRate>20.0604622</ExchangeRate>
         </ChargeDetails>
         <ChargeDetails>
            <ChargeCode>300</ChargeCode>
            <CreditDebitFlag>D</CreditDebitFlag>
            <ChargeDescription>Export Customs Clearance</ChargeDescription>
            <ChargeAmount>
               <Value>702.12</Value>
               <Currency>MXN</Currency>
            </ChargeAmount>
            <VATPercentage>0.00</VATPercentage>
            <ChargeRemarks/>
            <CalculationQuantity>
               <Value>0.001</Value>
            </CalculationQuantity>
            <CalculationRate>35.00</CalculationRate>
            <ForeignChargeAmount>
               <Value>35.00</Value>
               <Currency>EUR</Currency>
            </ForeignChargeAmount>
            <ExchangeRate>20.0604622</ExchangeRate>
         </ChargeDetails>
         <ChargeDetails>
            <ChargeCode>201</ChargeCode>
            <CreditDebitFlag>D</CreditDebitFlag>
            <ChargeDescription>B/L Fee Export</ChargeDescription>
            <ChargeAmount>
               <Value>501.51</Value>
               <Currency>MXN</Currency>
            </ChargeAmount>
            <VATPercentage>0.00</VATPercentage>
            <ChargeRemarks/>
            <CalculationQuantity>
               <Value>0.001</Value>
            </CalculationQuantity>
            <CalculationRate>25.00</CalculationRate>
            <ForeignChargeAmount>
               <Value>25.00</Value>
               <Currency>EUR</Currency>
            </ForeignChargeAmount>
            <ExchangeRate>20.0604622</ExchangeRate>
         </ChargeDetails>
         <ChargeDetails>
            <ChargeCode>220</ChargeCode>
            <CreditDebitFlag>D</CreditDebitFlag>
            <ChargeDescription>Handling Charge (FF)</ChargeDescription>
            <ChargeAmount>
               <Value>902.72</Value>
               <Currency>MXN</Currency>
            </ChargeAmount>
            <VATPercentage>0.00</VATPercentage>
            <ChargeRemarks/>
            <CalculationQuantity>
               <Value>0.001</Value>
            </CalculationQuantity>
            <CalculationRate>45.00</CalculationRate>
            <ForeignChargeAmount>
               <Value>45.00</Value>
               <Currency>EUR</Currency>
            </ForeignChargeAmount>
            <ExchangeRate>20.0604622</ExchangeRate>
         </ChargeDetails>
         <ChargeDetails>
            <ChargeCode>426</ChargeCode>
            <CreditDebitFlag>D</CreditDebitFlag>
            <ChargeDescription>Handling Charge Export</ChargeDescription>
            <ChargeAmount>
               <Value>521.57</Value>
               <Currency>MXN</Currency>
            </ChargeAmount>
            <VATPercentage>0.00</VATPercentage>
            <ChargeRemarks/>
            <CalculationQuantity>
               <Value>0.001</Value>
            </CalculationQuantity>
            <CalculationRate>26.00</CalculationRate>
            <ForeignChargeAmount>
               <Value>26.00</Value>
               <Currency>EUR</Currency>
            </ForeignChargeAmount>
            <ExchangeRate>20.0604622</ExchangeRate>
         </ChargeDetails>
         <ChargeDetails>
            <ChargeCode>581</ChargeCode>
            <CreditDebitFlag>D</CreditDebitFlag>
            <ChargeDescription>AMS/ACI Security Fee</ChargeDescription>
            <ChargeAmount>
               <Value>702.12</Value>
               <Currency>MXN</Currency>
            </ChargeAmount>
            <VATPercentage>0.00</VATPercentage>
            <ChargeRemarks/>
            <CalculationQuantity>
               <Value>0.001</Value>
            </CalculationQuantity>
            <CalculationRate>35.00</CalculationRate>
            <ForeignChargeAmount>
               <Value>35.00</Value>
               <Currency>EUR</Currency>
            </ForeignChargeAmount>
            <ExchangeRate>20.0604622</ExchangeRate>
         </ChargeDetails>
         <ChargeDetails>
            <ChargeCode>588</ChargeCode>
            <CreditDebitFlag>D</CreditDebitFlag>
            <ChargeDescription>Terminal Security Fee O.</ChargeDescription>
            <ChargeAmount>
               <Value>261.92</Value>
               <Currency>MXN</Currency>
            </ChargeAmount>
            <VATPercentage>16.00</VATPercentage>
            <ChargeRemarks/>
            <CalculationQuantity>
               <Value>0.001</Value>
            </CalculationQuantity>
            <CalculationRate>15.00</CalculationRate>
            <ForeignChargeAmount>
               <Value>15.00</Value>
               <Currency>USD</Currency>
            </ForeignChargeAmount>
            <ExchangeRate>17.461</ExchangeRate>
         </ChargeDetails>
         <ChargeDetails>
            <ChargeCode>965</ChargeCode>
            <CreditDebitFlag>D</CreditDebitFlag>
            <ChargeDescription>Additional Local Charges 1</ChargeDescription>
            <ChargeAmount>
               <Value>2095.32</Value>
               <Currency>MXN</Currency>
            </ChargeAmount>
            <VATPercentage>16.00</VATPercentage>
            <ChargeRemarks/>
            <CalculationQuantity>
               <Value>0.001</Value>
            </CalculationQuantity>
            <CalculationRate>120.00</CalculationRate>
            <ForeignChargeAmount>
               <Value>120.00</Value>
               <Currency>USD</Currency>
            </ForeignChargeAmount>
            <ExchangeRate>17.461</ExchangeRate>
         </ChargeDetails>
         <ChargeDetails>
            <ChargeCode>966</ChargeCode>
            <CreditDebitFlag>D</CreditDebitFlag>
            <ChargeDescription>Additional Local Charges 2</ChargeDescription>
            <ChargeAmount>
               <Value>995.28</Value>
               <Currency>MXN</Currency>
            </ChargeAmount>
            <VATPercentage>16.00</VATPercentage>
            <ChargeRemarks/>
            <CalculationQuantity>
               <Value>0.001</Value>
            </CalculationQuantity>
            <CalculationRate>57.00</CalculationRate>
            <ForeignChargeAmount>
               <Value>57.00</Value>
               <Currency>USD</Currency>
            </ForeignChargeAmount>
            <ExchangeRate>17.461</ExchangeRate>
         </ChargeDetails>
         <AddressInformation>
            <AddressType>CN</AddressType>
            <PartyInformation>
               <PartyName>Schering-Plough, S.A. de C.V.</PartyName>
               <Street>Calle 16 de Septiembre 301</Street>
               <City>Mexico</City>
               <StateRegionCode>DF</StateRegionCode>
               <CountryCode>MX</CountryCode>
               <KNAddressCode>1000138525</KNAddressCode>
            </PartyInformation>
         </AddressInformation>
         <AddressInformation>
            <AddressType>CU</AddressType>
            <PartyInformation>
               <PartyName>Schering-Plough, S.A. de C.V.</PartyName>
               <Street>Calle 16 de Septiembre 301</Street>
               <City>Mexico</City>
               <StateRegionCode>DF</StateRegionCode>
               <CountryCode>MX</CountryCode>
               <KNAddressCode>1000138525</KNAddressCode>
            </PartyInformation>
         </AddressInformation>
         <AddressInformation>
            <AddressType>NI</AddressType>
            <PartyInformation>
               <PartyName>Schering-Plough, S.A. de C.V.</PartyName>
               <Street>Calle 16 de Septiembre 301</Street>
               <City>Mexico</City>
               <StateRegionCode>DF</StateRegionCode>
               <CountryCode>MX</CountryCode>
               <KNAddressCode>1000138525</KNAddressCode>
            </PartyInformation>
         </AddressInformation>
         <AddressInformation>
            <AddressType>SH</AddressType>
            <PartyInformation>
               <PartyName>Constantia Patz Ges.m.b.H.</PartyName>
               <Street>Guntramserstrasse 7</Street>
               <City>Natschbach-Loipersbach</City>
               <CountryCode>AT</CountryCode>
               <KNAddressCode>1000236770</KNAddressCode>
            </PartyInformation>
         </AddressInformation>
         <ReferenceInformation>
            <AddressType>PF</AddressType>
            <ReferenceType>PRF</ReferenceType>
            <Reference>Standard: SPL910701FD9</Reference>
         </ReferenceInformation>
         <ReferenceInformation>
            <AddressType>CN</AddressType>
            <ReferenceType>CIV</ReferenceType>
            <Reference>.</Reference>
         </ReferenceInformation>
         <ReferenceInformation>
            <AddressType>CN</AddressType>
            <ReferenceType>CR</ReferenceType>
            <Reference>65</Reference>
         </ReferenceInformation>
         <ReferenceInformation>
            <AddressType>CN</AddressType>
            <ReferenceType>KN1</ReferenceType>
            <Reference>,</Reference>
         </ReferenceInformation>
         <ReferenceInformation>
            <AddressType>CN</AddressType>
            <ReferenceType>X01</ReferenceType>
            <Reference>OC 8101683648 API BULK</Reference>
         </ReferenceInformation>
         <ReferenceInformation>
            <AddressType>CN</AddressType>
            <ReferenceType>Z15</ReferenceType>
            <Reference>SP-MX-MEX-01-GE</Reference>
         </ReferenceInformation>
         <ReferenceInformation>
            <AddressType>SH</AddressType>
            <ReferenceType>Z15</ReferenceType>
            <Reference>CONSTANTIA AT</Reference>
         </ReferenceInformation>
         <ReferenceInformation>
            <AddressType>FF</AddressType>
            <ReferenceType>KNF</ReferenceType>
            <Reference>LNZS12017029</Reference>
         </ReferenceInformation>
         <ReferenceInformation>
            <AddressType>FF</AddressType>
            <ReferenceType>KNF</ReferenceType>
            <Reference>1830-0858-603.011</Reference>
         </ReferenceInformation>
         <ReferenceInformation>
            <AddressType>FF</AddressType>
            <ReferenceType>KNF</ReferenceType>
            <Reference>10470120160401100</Reference>
         </ReferenceInformation>
         <ReferenceInformation>
            <AddressType>FF</AddressType>
            <ReferenceType>KNF</ReferenceType>
            <Reference>0073</Reference>
         </ReferenceInformation>
         <ShipmentInformation>
            <ModeOfTransport>SEA</ModeOfTransport>
            <TotalNoOfPackages>1</TotalNoOfPackages>
            <DangerousGoodsFlag>N</DangerousGoodsFlag>
            <TotalGrossWeight>
               <Value>307.00</Value>
               <MeasureUnit>K</MeasureUnit>
            </TotalGrossWeight>
            <TotalChargeableWeight>
               <Value>0.00</Value>
               <MeasureUnit>K</MeasureUnit>
            </TotalChargeableWeight>
            <TotalGrossVolume>
               <Value>0.682</Value>
               <MeasureUnit>M</MeasureUnit>
            </TotalGrossVolume>
            <ShippingDetails>
               <Seafreight>
                  <PlaceOfReceipt>LOIPERSBACH</PlaceOfReceipt>
                  <CountryOfOrigin>BE</CountryOfOrigin>
                  <PortOfLoading>BEANR</PortOfLoading>
                  <ETSDate>2016-03-15</ETSDate>
                  <ETADate>2016-04-01</ETADate>
                  <PortOfDischarge>MXVER</PortOfDischarge>
                  <CountryOfDestination>MX</CountryOfDestination>
                  <OceanVessel>CSL VIRGINIA</OceanVessel>
                  <VoyageNo>008W</VoyageNo>
                  <SCAC/>
                  <TermsOfDelivery>EXW</TermsOfDelivery>
                  <TermsOfDeliveryLocation>LOIPERSBACH</TermsOfDeliveryLocation>
                  <InsuranceCode>0</InsuranceCode>
               </Seafreight>
            </ShippingDetails>
         </ShipmentInformation>
      </InvoiceDetails>
      <InvoiceTotals>
         <InvoiceTotalIncludingVAT>
            <Value>15829.10</Value>
            <Currency>MXN</Currency>
            <VATPercentage>0.00</VATPercentage>
         </InvoiceTotalIncludingVAT>
         <InvoiceNetLiableVAT>
            <Value>536.40</Value>
            <Currency>MXN</Currency>
            <VATPercentage>0.00</VATPercentage>
         </InvoiceNetLiableVAT>
         <InvoiceNetNotLiableVAT>
            <Value>0.00</Value>
            <Currency>MXN</Currency>
         </InvoiceNetNotLiableVAT>
         <InvoiceTotalVAT>
            <Value>536.40</Value>
            <Currency>MXN</Currency>
            <VATPercentage>0.00</VATPercentage>
         </InvoiceTotalVAT>
         <InvoiceTotalNet>
            <Value>3352.52</Value>
            <Currency>MXN</Currency>
         </InvoiceTotalNet>
      </InvoiceTotals>
      <InvoiceTotals>
         <InvoiceTotalIncludingVAT>
            <Value>15829.10</Value>
            <Currency>MXN</Currency>
            <VATPercentage>0.00</VATPercentage>
         </InvoiceTotalIncludingVAT>
         <InvoiceNetLiableVAT>
            <Value>0.00</Value>
            <Currency>MXN</Currency>
            <VATPercentage>0.00</VATPercentage>
         </InvoiceNetLiableVAT>
         <InvoiceNetNotLiableVAT>
            <Value>0.00</Value>
            <Currency>MXN</Currency>
         </InvoiceNetNotLiableVAT>
         <InvoiceTotalVAT>
            <Value>0.00</Value>
            <Currency>MXN</Currency>
            <VATPercentage>0.00</VATPercentage>
         </InvoiceTotalVAT>
         <InvoiceTotalNet>
            <Value>11940.18</Value>
            <Currency>MXN</Currency>
         </InvoiceTotalNet>
      </InvoiceTotals>
   </Message>
</FreightInvoiceExt>